{
  "Targets" : {
    "dns" : {
      "Total": { "Count":    15, "Percentage":  1.784 },
      "Redundancy":  0.267,
      "Signatures": {
        "#1":   { "Count":     0, "Percentage":  0.000 },
        "#2":   { "Count":     0, "Percentage":  0.000 },
        "#3":   { "Count":     0, "Percentage":  0.000 },
        "#4":   { "Count":     0, "Percentage":  0.000 },
        "#5":   { "Count":     0, "Percentage":  0.000 },
        "#6":   { "Count":     0, "Percentage":  0.000 },
        "#7":   { "Count":     0, "Percentage":  0.000 },
        "#8":   { "Count":     0, "Percentage":  0.000 },
        "#9":   { "Count":     0, "Percentage":  0.000 },
        "#10":  { "Count":     0, "Percentage":  0.000 },
        "#11":  { "Count":     0, "Percentage":  0.000 },
        "#12":  { "Count":     0, "Percentage":  0.000 },
        "#13":  { "Count":     0, "Percentage":  0.000 },
        "#14":  { "Count":     0, "Percentage":  0.000 },
        "#15":  { "Count":     0, "Percentage":  0.000 },
        "#16":  { "Count":     0, "Percentage":  0.000 },
        "#17":  { "Count":     4, "Percentage":  0.476 },
        "#18":  { "Count":     0, "Percentage":  0.000 },
        "#19":  { "Count":     0, "Percentage":  0.000 },
        "#20":  { "Count":     0, "Percentage":  0.000 },
        "#21":  { "Count":     0, "Percentage":  0.000 },
        "#22":  { "Count":     0, "Percentage":  0.000 },
        "#23":  { "Count":    15, "Percentage":  1.784 },
        "#24":  { "Count":     0, "Percentage":  0.000 },
        "#25":  { "Count":     4, "Percentage":  0.476 },
        "#26":  { "Count":     2, "Percentage":  0.238 },
        "#27":  { "Count":     0, "Percentage":  0.000 },
        "#28":  { "Count":     0, "Percentage":  0.000 },
        "#29":  { "Count":     0, "Percentage":  0.000 },
        "#30":  { "Count":     0, "Percentage":  0.000 },
        "#31":  { "Count":     0, "Percentage":  0.000 },
        "#32":  { "Count":     0, "Percentage":  0.000 },
        "#33":  { "Count":     0, "Percentage":  0.000 },
        "#34":  { "Count":     0, "Percentage":  0.000 },
        "#35":  { "Count":     0, "Percentage":  0.000 },
        "#36":  { "Count":     0, "Percentage":  0.000 },
        "#37":  { "Count":     0, "Percentage":  0.000 },
        "#38":  { "Count":     0, "Percentage":  0.000 },
        "#39":  { "Count":     0, "Percentage":  0.000 },
        "#40":  { "Count":     4, "Percentage":  0.476 },
        "#41":  { "Count":     0, "Percentage":  0.000 },
        "#42":  { "Count":     0, "Percentage":  0.000 },
        "#43":  { "Count":     0, "Percentage":  0.000 },
        "#44":  { "Count":     0, "Percentage":  0.000 },
        "#45":  { "Count":     0, "Percentage":  0.000 },
        "#46":  { "Count":     0, "Percentage":  0.000 },
        "#47":  { "Count":     0, "Percentage":  0.000 },
        "#48":  { "Count":     0, "Percentage":  0.000 },
        "#49":  { "Count":     0, "Percentage":  0.000 },
        "#50":  { "Count":     0, "Percentage":  0.000 },
        "#51":  { "Count":     4, "Percentage":  0.476 },
        "#52":  { "Count":     0, "Percentage":  0.000 },
        "#53":  { "Count":     4, "Percentage":  0.476 },
        "#54":  { "Count":     0, "Percentage":  0.000 },
        "#55":  { "Count":     0, "Percentage":  0.000 },
        "#56":  { "Count":     0, "Percentage":  0.000 },
        "#57":  { "Count":     0, "Percentage":  0.000 },
        "#58":  { "Count":     0, "Percentage":  0.000 },
        "#59":  { "Count":     0, "Percentage":  0.000 }
      }
    },
    "pop" : {
      "Total": { "Count":     0, "Percentage":  0.000 },
      "Signatures": {
        "#1":   { "Count":     0, "Percentage":  0.000 },
        "#2":   { "Count":     0, "Percentage":  0.000 }
      }
    },
    "smtp" : {
      "Total": { "Count":     1, "Percentage":  0.119 },
      "Redundancy":  1.000,
      "Signatures": {
        "#1":   { "Count":     0, "Percentage":  0.000 },
        "#2":   { "Count":     0, "Percentage":  0.000 },
        "#3":   { "Count":     0, "Percentage":  0.000 },
        "#4":   { "Count":     0, "Percentage":  0.000 },
        "#5":   { "Count":     0, "Percentage":  0.000 },
        "#6":   { "Count":     0, "Percentage":  0.000 },
        "#7":   { "Count":     0, "Percentage":  0.000 },
        "#8":   { "Count":     0, "Percentage":  0.000 },
        "#9":   { "Count":     0, "Percentage":  0.000 },
        "#10":  { "Count":     0, "Percentage":  0.000 },
        "#11":  { "Count":     0, "Percentage":  0.000 },
        "#12":  { "Count":     0, "Percentage":  0.000 },
        "#13":  { "Count":     0, "Percentage":  0.000 },
        "#14":  { "Count":     0, "Percentage":  0.000 },
        "#15":  { "Count":     0, "Percentage":  0.000 },
        "#16":  { "Count":     0, "Percentage":  0.000 },
        "#17":  { "Count":     0, "Percentage":  0.000 },
        "#18":  { "Count":     0, "Percentage":  0.000 },
        "#19":  { "Count":     0, "Percentage":  0.000 },
        "#20":  { "Count":     0, "Percentage":  0.000 },
        "#21":  { "Count":     0, "Percentage":  0.000 },
        "#22":  { "Count":     0, "Percentage":  0.000 },
        "#23":  { "Count":     0, "Percentage":  0.000 },
        "#24":  { "Count":     0, "Percentage":  0.000 },
        "#25":  { "Count":     0, "Percentage":  0.000 },
        "#26":  { "Count":     0, "Percentage":  0.000 },
        "#27":  { "Count":     0, "Percentage":  0.000 },
        "#28":  { "Count":     0, "Percentage":  0.000 },
        "#29":  { "Count":     0, "Percentage":  0.000 },
        "#30":  { "Count":     0, "Percentage":  0.000 },
        "#31":  { "Count":     0, "Percentage":  0.000 },
        "#32":  { "Count":     0, "Percentage":  0.000 },
        "#33":  { "Count":     0, "Percentage":  0.000 },
        "#34":  { "Count":     0, "Percentage":  0.000 },
        "#35":  { "Count":     0, "Percentage":  0.000 },
        "#36":  { "Count":     0, "Percentage":  0.000 },
        "#37":  { "Count":     0, "Percentage":  0.000 },
        "#38":  { "Count":     0, "Percentage":  0.000 },
        "#39":  { "Count":     0, "Percentage":  0.000 },
        "#40":  { "Count":     0, "Percentage":  0.000 },
        "#41":  { "Count":     0, "Percentage":  0.000 },
        "#42":  { "Count":     0, "Percentage":  0.000 },
        "#43":  { "Count":     0, "Percentage":  0.000 },
        "#44":  { "Count":     0, "Percentage":  0.000 },
        "#45":  { "Count":     0, "Percentage":  0.000 },
        "#46":  { "Count":     0, "Percentage":  0.000 },
        "#47":  { "Count":     0, "Percentage":  0.000 },
        "#48":  { "Count":     0, "Percentage":  0.000 },
        "#49":  { "Count":     0, "Percentage":  0.000 },
        "#50":  { "Count":     0, "Percentage":  0.000 },
        "#51":  { "Count":     0, "Percentage":  0.000 },
        "#52":  { "Count":     0, "Percentage":  0.000 },
        "#53":  { "Count":     0, "Percentage":  0.000 },
        "#54":  { "Count":     0, "Percentage":  0.000 },
        "#55":  { "Count":     0, "Percentage":  0.000 },
        "#56":  { "Count":     0, "Percentage":  0.000 },
        "#57":  { "Count":     0, "Percentage":  0.000 },
        "#58":  { "Count":     0, "Percentage":  0.000 },
        "#59":  { "Count":     0, "Percentage":  0.000 },
        "#60":  { "Count":     0, "Percentage":  0.000 },
        "#61":  { "Count":     0, "Percentage":  0.000 },
        "#62":  { "Count":     0, "Percentage":  0.000 },
        "#63":  { "Count":     0, "Percentage":  0.000 },
        "#64":  { "Count":     0, "Percentage":  0.000 },
        "#65":  { "Count":     0, "Percentage":  0.000 },
        "#66":  { "Count":     0, "Percentage":  0.000 },
        "#67":  { "Count":     0, "Percentage":  0.000 },
        "#68":  { "Count":     0, "Percentage":  0.000 },
        "#69":  { "Count":     0, "Percentage":  0.000 },
        "#70":  { "Count":     0, "Percentage":  0.000 },
        "#71":  { "Count":     0, "Percentage":  0.000 },
        "#72":  { "Count":     0, "Percentage":  0.000 },
        "#73":  { "Count":     0, "Percentage":  0.000 },
        "#74":  { "Count":     0, "Percentage":  0.000 },
        "#75":  { "Count":     0, "Percentage":  0.000 },
        "#76":  { "Count":     0, "Percentage":  0.000 },
        "#77":  { "Count":     0, "Percentage":  0.000 },
        "#78":  { "Count":     0, "Percentage":  0.000 },
        "#79":  { "Count":     0, "Percentage":  0.000 },
        "#80":  { "Count":     0, "Percentage":  0.000 },
        "#81":  { "Count":     0, "Percentage":  0.000 },
        "#82":  { "Count":     0, "Percentage":  0.000 },
        "#83":  { "Count":     0, "Percentage":  0.000 },
        "#84":  { "Count":     0, "Percentage":  0.000 },
        "#85":  { "Count":     0, "Percentage":  0.000 },
        "#86":  { "Count":     0, "Percentage":  0.000 },
        "#87":  { "Count":     0, "Percentage":  0.000 },
        "#88":  { "Count":     0, "Percentage":  0.000 },
        "#89":  { "Count":     0, "Percentage":  0.000 },
        "#90":  { "Count":     0, "Percentage":  0.000 },
        "#91":  { "Count":     0, "Percentage":  0.000 },
        "#92":  { "Count":     0, "Percentage":  0.000 },
        "#93":  { "Count":     0, "Percentage":  0.000 },
        "#94":  { "Count":     0, "Percentage":  0.000 },
        "#95":  { "Count":     0, "Percentage":  0.000 },
        "#96":  { "Count":     0, "Percentage":  0.000 },
        "#97":  { "Count":     0, "Percentage":  0.000 },
        "#98":  { "Count":     0, "Percentage":  0.000 },
        "#99":  { "Count":     0, "Percentage":  0.000 },
        "#100": { "Count":     0, "Percentage":  0.000 },
        "#101": { "Count":     0, "Percentage":  0.000 },
        "#102": { "Count":     0, "Percentage":  0.000 },
        "#103": { "Count":     0, "Percentage":  0.000 },
        "#104": { "Count":     0, "Percentage":  0.000 },
        "#105": { "Count":     0, "Percentage":  0.000 },
        "#106": { "Count":     0, "Percentage":  0.000 },
        "#107": { "Count":     0, "Percentage":  0.000 },
        "#108": { "Count":     0, "Percentage":  0.000 },
        "#109": { "Count":     0, "Percentage":  0.000 },
        "#110": { "Count":     0, "Percentage":  0.000 },
        "#111": { "Count":     0, "Percentage":  0.000 },
        "#112": { "Count":     0, "Percentage":  0.000 },
        "#113": { "Count":     0, "Percentage":  0.000 },
        "#114": { "Count":     0, "Percentage":  0.000 },
        "#115": { "Count":     0, "Percentage":  0.000 },
        "#116": { "Count":     0, "Percentage":  0.000 },
        "#117": { "Count":     0, "Percentage":  0.000 },
        "#118": { "Count":     0, "Percentage":  0.000 },
        "#119": { "Count":     0, "Percentage":  0.000 },
        "#120": { "Count":     0, "Percentage":  0.000 },
        "#121": { "Count":     0, "Percentage":  0.000 },
        "#122": { "Count":     0, "Percentage":  0.000 },
        "#123": { "Count":     0, "Percentage":  0.000 },
        "#124": { "Count":     0, "Percentage":  0.000 },
        "#125": { "Count":     0, "Percentage":  0.000 },
        "#126": { "Count":     0, "Percentage":  0.000 },
        "#127": { "Count":     0, "Percentage":  0.000 },
        "#128": { "Count":     0, "Percentage":  0.000 },
        "#129": { "Count":     0, "Percentage":  0.000 },
        "#130": { "Count":     0, "Percentage":  0.000 },
        "#131": { "Count":     0, "Percentage":  0.000 },
        "#132": { "Count":     0, "Percentage":  0.000 },
        "#133": { "Count":     0, "Percentage":  0.000 },
        "#134": { "Count":     0, "Percentage":  0.000 },
        "#135": { "Count":     0, "Percentage":  0.000 },
        "#136": { "Count":     0, "Percentage":  0.000 },
        "#137": { "Count":     0, "Percentage":  0.000 },
        "#138": { "Count":     0, "Percentage":  0.000 },
        "#139": { "Count":     0, "Percentage":  0.000 },
        "#140": { "Count":     0, "Percentage":  0.000 },
        "#141": { "Count":     0, "Percentage":  0.000 },
        "#142": { "Count":     0, "Percentage":  0.000 },
        "#143": { "Count":     0, "Percentage":  0.000 },
        "#144": { "Count":     0, "Percentage":  0.000 },
        "#145": { "Count":     0, "Percentage":  0.000 },
        "#146": { "Count":     0, "Percentage":  0.000 },
        "#147": { "Count":     0, "Percentage":  0.000 },
        "#148": { "Count":     0, "Percentage":  0.000 },
        "#149": { "Count":     1, "Percentage":  0.119 },
        "#150": { "Count":     1, "Percentage":  0.119 },
        "#151": { "Count":     0, "Percentage":  0.000 },
        "#152": { "Count":     0, "Percentage":  0.000 },
        "#153": { "Count":     0, "Percentage":  0.000 },
        "#154": { "Count":     0, "Percentage":  0.000 },
        "#155": { "Count":     0, "Percentage":  0.000 },
        "#156": { "Count":     0, "Percentage":  0.000 },
        "#157": { "Count":     0, "Percentage":  0.000 },
        "#158": { "Count":     0, "Percentage":  0.000 },
        "#159": { "Count":     0, "Percentage":  0.000 },
        "#160": { "Count":     0, "Percentage":  0.000 },
        "#161": { "Count":     0, "Percentage":  0.000 },
        "#162": { "Count":     0, "Percentage":  0.000 },
        "#163": { "Count":     0, "Percentage":  0.000 },
        "#164": { "Count":     0, "Percentage":  0.000 },
        "#165": { "Count":     0, "Percentage":  0.000 },
        "#166": { "Count":     0, "Percentage":  0.000 },
        "#167": { "Count":     0, "Percentage":  0.000 },
        "#168": { "Count":     0, "Percentage":  0.000 },
        "#169": { "Count":     0, "Percentage":  0.000 },
        "#170": { "Count":     0, "Percentage":  0.000 },
        "#171": { "Count":     0, "Percentage":  0.000 },
        "#172": { "Count":     0, "Percentage":  0.000 },
        "#173": { "Count":     0, "Percentage":  0.000 },
        "#174": { "Count":     0, "Percentage":  0.000 },
        "#175": { "Count":     0, "Percentage":  0.000 },
        "#176": { "Count":     0, "Percentage":  0.000 },
        "#177": { "Count":     0, "Percentage":  0.000 },
        "#178": { "Count":     0, "Percentage":  0.000 },
        "#179": { "Count":     0, "Percentage":  0.000 },
        "#180": { "Count":     0, "Percentage":  0.000 },
        "#181": { "Count":     0, "Percentage":  0.000 },
        "#182": { "Count":     0, "Percentage":  0.000 },
        "#183": { "Count":     0, "Percentage":  0.000 },
        "#184": { "Count":     0, "Percentage":  0.000 },
        "#185": { "Count":     0, "Percentage":  0.000 },
        "#186": { "Count":     0, "Percentage":  0.000 },
        "#187": { "Count":     0, "Percentage":  0.000 },
        "#188": { "Count":     0, "Percentage":  0.000 },
        "#189": { "Count":     0, "Percentage":  0.000 },
        "#190": { "Count":     0, "Percentage":  0.000 },
        "#191": { "Count":     0, "Percentage":  0.000 },
        "#192": { "Count":     0, "Percentage":  0.000 },
        "#193": { "Count":     0, "Percentage":  0.000 },
        "#194": { "Count":     0, "Percentage":  0.000 },
        "#195": { "Count":     0, "Percentage":  0.000 },
        "#196": { "Count":     0, "Percentage":  0.000 },
        "#197": { "Count":     0, "Percentage":  0.000 },
        "#198": { "Count":     0, "Percentage":  0.000 },
        "#199": { "Count":     0, "Percentage":  0.000 },
        "#200": { "Count":     0, "Percentage":  0.000 },
        "#201": { "Count":     0, "Percentage":  0.000 },
        "#202": { "Count":     0, "Percentage":  0.000 },
        "#203": { "Count":     0, "Percentage":  0.000 },
        "#204": { "Count":     0, "Percentage":  0.000 },
        "#205": { "Count":     0, "Percentage":  0.000 },
        "#206": { "Count":     0, "Percentage":  0.000 },
        "#207": { "Count":     0, "Percentage":  0.000 },
        "#208": { "Count":     0, "Percentage":  0.000 },
        "#209": { "Count":     0, "Percentage":  0.000 },
        "#210": { "Count":     0, "Percentage":  0.000 },
        "#211": { "Count":     0, "Percentage":  0.000 },
        "#212": { "Count":     0, "Percentage":  0.000 },
        "#213": { "Count":     0, "Percentage":  0.000 },
        "#214": { "Count":     0, "Percentage":  0.000 },
        "#215": { "Count":     0, "Percentage":  0.000 },
        "#216": { "Count":     0, "Percentage":  0.000 },
        "#217": { "Count":     0, "Percentage":  0.000 },
        "#218": { "Count":     0, "Percentage":  0.000 },
        "#219": { "Count":     0, "Percentage":  0.000 },
        "#220": { "Count":     0, "Percentage":  0.000 },
        "#221": { "Count":     0, "Percentage":  0.000 },
        "#222": { "Count":     0, "Percentage":  0.000 },
        "#223": { "Count":     0, "Percentage":  0.000 },
        "#224": { "Count":     0, "Percentage":  0.000 },
        "#225": { "Count":     0, "Percentage":  0.000 },
        "#226": { "Count":     0, "Percentage":  0.000 },
        "#227": { "Count":     0, "Percentage":  0.000 },
        "#228": { "Count":     0, "Percentage":  0.000 },
        "#229": { "Count":     0, "Percentage":  0.000 },
        "#230": { "Count":     0, "Percentage":  0.000 },
        "#231": { "Count":     0, "Percentage":  0.000 },
        "#232": { "Count":     0, "Percentage":  0.000 },
        "#233": { "Count":     0, "Percentage":  0.000 },
        "#234": { "Count":     0, "Percentage":  0.000 },
        "#235": { "Count":     0, "Percentage":  0.000 },
        "#236": { "Count":     0, "Percentage":  0.000 },
        "#237": { "Count":     0, "Percentage":  0.000 },
        "#238": { "Count":     0, "Percentage":  0.000 },
        "#239": { "Count":     0, "Percentage":  0.000 },
        "#240": { "Count":     0, "Percentage":  0.000 },
        "#241": { "Count":     0, "Percentage":  0.000 },
        "#242": { "Count":     0, "Percentage":  0.000 },
        "#243": { "Count":     0, "Percentage":  0.000 },
        "#244": { "Count":     0, "Percentage":  0.000 },
        "#245": { "Count":     0, "Percentage":  0.000 },
        "#246": { "Count":     0, "Percentage":  0.000 },
        "#247": { "Count":     0, "Percentage":  0.000 },
        "#248": { "Count":     0, "Percentage":  0.000 },
        "#249": { "Count":     0, "Percentage":  0.000 },
        "#250": { "Count":     0, "Percentage":  0.000 },
        "#251": { "Count":     0, "Percentage":  0.000 },
        "#252": { "Count":     0, "Percentage":  0.000 },
        "#253": { "Count":     0, "Percentage":  0.000 },
        "#254": { "Count":     0, "Percentage":  0.000 },
        "#255": { "Count":     0, "Percentage":  0.000 },
        "#256": { "Count":     0, "Percentage":  0.000 },
        "#257": { "Count":     0, "Percentage":  0.000 },
        "#258": { "Count":     0, "Percentage":  0.000 },
        "#259": { "Count":     0, "Percentage":  0.000 },
        "#260": { "Count":     0, "Percentage":  0.000 },
        "#261": { "Count":     0, "Percentage":  0.000 },
        "#262": { "Count":     0, "Percentage":  0.000 },
        "#263": { "Count":     0, "Percentage":  0.000 },
        "#264": { "Count":     0, "Percentage":  0.000 },
        "#265": { "Count":     0, "Percentage":  0.000 },
        "#266": { "Count":     0, "Percentage":  0.000 },
        "#267": { "Count":     0, "Percentage":  0.000 },
        "#268": { "Count":     0, "Percentage":  0.000 },
        "#269": { "Count":     0, "Percentage":  0.000 },
        "#270": { "Count":     0, "Percentage":  0.000 },
        "#271": { "Count":     0, "Percentage":  0.000 },
        "#272": { "Count":     0, "Percentage":  0.000 },
        "#273": { "Count":     0, "Percentage":  0.000 },
        "#274": { "Count":     0, "Percentage":  0.000 },
        "#275": { "Count":     0, "Percentage":  0.000 },
        "#276": { "Count":     0, "Percentage":  0.000 },
        "#277": { "Count":     0, "Percentage":  0.000 },
        "#278": { "Count":     0, "Percentage":  0.000 },
        "#279": { "Count":     0, "Percentage":  0.000 },
        "#280": { "Count":     0, "Percentage":  0.000 },
        "#281": { "Count":     0, "Percentage":  0.000 },
        "#282": { "Count":     0, "Percentage":  0.000 },
        "#283": { "Count":     0, "Percentage":  0.000 },
        "#284": { "Count":     0, "Percentage":  0.000 },
        "#285": { "Count":     0, "Percentage":  0.000 },
        "#286": { "Count":     0, "Percentage":  0.000 },
        "#287": { "Count":     0, "Percentage":  0.000 },
        "#288": { "Count":     0, "Percentage":  0.000 },
        "#289": { "Count":     0, "Percentage":  0.000 },
        "#290": { "Count":     0, "Percentage":  0.000 },
        "#291": { "Count":     0, "Percentage":  0.000 },
        "#292": { "Count":     0, "Percentage":  0.000 },
        "#293": { "Count":     0, "Percentage":  0.000 },
        "#294": { "Count":     0, "Percentage":  0.000 },
        "#295": { "Count":     0, "Percentage":  0.000 },
        "#296": { "Count":     0, "Percentage":  0.000 },
        "#297": { "Count":     0, "Percentage":  0.000 },
        "#298": { "Count":     0, "Percentage":  0.000 },
        "#299": { "Count":     0, "Percentage":  0.000 },
        "#300": { "Count":     0, "Percentage":  0.000 },
        "#301": { "Count":     0, "Percentage":  0.000 },
        "#302": { "Count":     0, "Percentage":  0.000 },
        "#303": { "Count":     0, "Percentage":  0.000 },
        "#304": { "Count":     0, "Percentage":  0.000 },
        "#305": { "Count":     0, "Percentage":  0.000 },
        "#306": { "Count":     0, "Percentage":  0.000 },
        "#307": { "Count":     0, "Percentage":  0.000 },
        "#308": { "Count":     0, "Percentage":  0.000 },
        "#309": { "Count":     0, "Percentage":  0.000 },
        "#310": { "Count":     0, "Percentage":  0.000 },
        "#311": { "Count":     0, "Percentage":  0.000 },
        "#312": { "Count":     0, "Percentage":  0.000 },
        "#313": { "Count":     0, "Percentage":  0.000 },
        "#314": { "Count":     0, "Percentage":  0.000 },
        "#315": { "Count":     0, "Percentage":  0.000 },
        "#316": { "Count":     0, "Percentage":  0.000 },
        "#317": { "Count":     0, "Percentage":  0.000 },
        "#318": { "Count":     0, "Percentage":  0.000 },
        "#319": { "Count":     0, "Percentage":  0.000 },
        "#320": { "Count":     0, "Percentage":  0.000 },
        "#321": { "Count":     0, "Percentage":  0.000 },
        "#322": { "Count":     0, "Percentage":  0.000 },
        "#323": { "Count":     0, "Percentage":  0.000 },
        "#324": { "Count":     0, "Percentage":  0.000 },
        "#325": { "Count":     0, "Percentage":  0.000 },
        "#326": { "Count":     0, "Percentage":  0.000 },
        "#327": { "Count":     0, "Percentage":  0.000 },
        "#328": { "Count":     0, "Percentage":  0.000 },
        "#329": { "Count":     0, "Percentage":  0.000 },
        "#330": { "Count":     0, "Percentage":  0.000 },
        "#331": { "Count":     0, "Percentage":  0.000 },
        "#332": { "Count":     0, "Percentage":  0.000 },
        "#333": { "Count":     0, "Percentage":  0.000 },
        "#334": { "Count":     0, "Percentage":  0.000 },
        "#335": { "Count":     0, "Percentage":  0.000 },
        "#336": { "Count":     0, "Percentage":  0.000 },
        "#337": { "Count":     0, "Percentage":  0.000 },
        "#338": { "Count":     0, "Percentage":  0.000 },
        "#339": { "Count":     0, "Percentage":  0.000 },
        "#340": { "Count":     0, "Percentage":  0.000 },
        "#341": { "Count":     0, "Percentage":  0.000 },
        "#342": { "Count":     0, "Percentage":  0.000 },
        "#343": { "Count":     0, "Percentage":  0.000 },
        "#344": { "Count":     0, "Percentage":  0.000 },
        "#345": { "Count":     0, "Percentage":  0.000 },
        "#346": { "Count":     0, "Percentage":  0.000 },
        "#347": { "Count":     0, "Percentage":  0.000 },
        "#348": { "Count":     0, "Percentage":  0.000 },
        "#349": { "Count":     0, "Percentage":  0.000 },
        "#350": { "Count":     0, "Percentage":  0.000 },
        "#351": { "Count":     0, "Percentage":  0.000 },
        "#352": { "Count":     0, "Percentage":  0.000 },
        "#353": { "Count":     0, "Percentage":  0.000 },
        "#354": { "Count":     0, "Percentage":  0.000 },
        "#355": { "Count":     0, "Percentage":  0.000 },
        "#356": { "Count":     0, "Percentage":  0.000 },
        "#357": { "Count":     0, "Percentage":  0.000 },
        "#358": { "Count":     0, "Percentage":  0.000 },
        "#359": { "Count":     0, "Percentage":  0.000 },
        "#360": { "Count":     0, "Percentage":  0.000 },
        "#361": { "Count":     0, "Percentage":  0.000 },
        "#362": { "Count":     0, "Percentage":  0.000 },
        "#363": { "Count":     0, "Percentage":  0.000 },
        "#364": { "Count":     0, "Percentage":  0.000 },
        "#365": { "Count":     0, "Percentage":  0.000 },
        "#366": { "Count":     0, "Percentage":  0.000 },
        "#367": { "Count":     0, "Percentage":  0.000 },
        "#368": { "Count":     0, "Percentage":  0.000 },
        "#369": { "Count":     0, "Percentage":  0.000 },
        "#370": { "Count":     0, "Percentage":  0.000 },
        "#371": { "Count":     0, "Percentage":  0.000 },
        "#372": { "Count":     0, "Percentage":  0.000 },
        "#373": { "Count":     0, "Percentage":  0.000 },
        "#374": { "Count":     0, "Percentage":  0.000 },
        "#375": { "Count":     0, "Percentage":  0.000 },
        "#376": { "Count":     0, "Percentage":  0.000 },
        "#377": { "Count":     0, "Percentage":  0.000 },
        "#378": { "Count":     0, "Percentage":  0.000 },
        "#379": { "Count":     0, "Percentage":  0.000 },
        "#380": { "Count":     0, "Percentage":  0.000 },
        "#381": { "Count":     0, "Percentage":  0.000 },
        "#382": { "Count":     0, "Percentage":  0.000 },
        "#383": { "Count":     0, "Percentage":  0.000 },
        "#384": { "Count":     0, "Percentage":  0.000 },
        "#385": { "Count":     0, "Percentage":  0.000 },
        "#386": { "Count":     0, "Percentage":  0.000 },
        "#387": { "Count":     0, "Percentage":  0.000 },
        "#388": { "Count":     0, "Percentage":  0.000 },
        "#389": { "Count":     0, "Percentage":  0.000 },
        "#390": { "Count":     0, "Percentage":  0.000 },
        "#391": { "Count":     0, "Percentage":  0.000 },
        "#392": { "Count":     0, "Percentage":  0.000 },
        "#393": { "Count":     0, "Percentage":  0.000 },
        "#394": { "Count":     0, "Percentage":  0.000 },
        "#395": { "Count":     0, "Percentage":  0.000 },
        "#396": { "Count":     0, "Percentage":  0.000 },
        "#397": { "Count":     0, "Percentage":  0.000 },
        "#398": { "Count":     0, "Percentage":  0.000 },
        "#399": { "Count":     0, "Percentage":  0.000 },
        "#400": { "Count":     0, "Percentage":  0.000 },
        "#401": { "Count":     0, "Percentage":  0.000 }
      }
    },
    "imap" : {
      "Total": { "Count":     0, "Percentage":  0.000 },
      "Signatures": {
        "#1":   { "Count":     0, "Percentage":  0.000 },
        "#2":   { "Count":     0, "Percentage":  0.000 },
        "#3":   { "Count":     0, "Percentage":  0.000 },
        "#4":   { "Count":     0, "Percentage":  0.000 },
        "#5":   { "Count":     0, "Percentage":  0.000 },
        "#6":   { "Count":     0, "Percentage":  0.000 },
        "#7":   { "Count":     0, "Percentage":  0.000 },
        "#8":   { "Count":     0, "Percentage":  0.000 },
        "#9":   { "Count":     0, "Percentage":  0.000 },
        "#10":  { "Count":     0, "Percentage":  0.000 },
        "#11":  { "Count":     0, "Percentage":  0.000 },
        "#12":  { "Count":     0, "Percentage":  0.000 },
        "#13":  { "Count":     0, "Percentage":  0.000 },
        "#14":  { "Count":     0, "Percentage":  0.000 },
        "#15":  { "Count":     0, "Percentage":  0.000 }
      }
    },
    "bittorrent" : {
      "Total": { "Count":   825, "Percentage": 98.098 },
      "Redundancy":  1.000,
      "Signatures": {
        "#1":   { "Count":   275, "Percentage": 32.699 },
        "#2":   { "Count":   275, "Percentage": 32.699 },
        "#3":   { "Count":   275, "Percentage": 32.699 },
        "#4":   { "Count":   275, "Percentage": 32.699 },
        "#5":   { "Count":   825, "Percentage": 98.098 },
        "#6":   { "Count":   275, "Percentage": 32.699 },
        "#7":   { "Count":   275, "Percentage": 32.699 },
        "#8":   { "Count":   277, "Percentage": 32.937 },
        "#9":   { "Count":   275, "Percentage": 32.699 },
        "#10":  { "Count":   275, "Percentage": 32.699 },
        "#11":  { "Count":   275, "Percentage": 32.699 },
        "#12":  { "Count":   275, "Percentage": 32.699 },
        "#13":  { "Count":   825, "Percentage": 98.098 },
        "#14":  { "Count":   275, "Percentage": 32.699 },
        "#15":  { "Count":   275, "Percentage": 32.699 },
        "#16":  { "Count":   213, "Percentage": 25.327 },
        "#17":  { "Count":   275, "Percentage": 32.699 },
        "#18":  { "Count":   275, "Percentage": 32.699 },
        "#19":  { "Count":   275, "Percentage": 32.699 },
        "#20":  { "Count":   275, "Percentage": 32.699 },
        "#21":  { "Count":   275, "Percentage": 32.699 },
        "#22":  { "Count":   275, "Percentage": 32.699 },
        "#23":  { "Count":   275, "Percentage": 32.699 },
        "#24":  { "Count":   275, "Percentage": 32.699 },
        "#25":  { "Count":   275, "Percentage": 32.699 },
        "#26":  { "Count":   275, "Percentage": 32.699 },
        "#27":  { "Count":   275, "Percentage": 32.699 },
        "#28":  { "Count":   275, "Percentage": 32.699 },
        "#29":  { "Count":   275, "Percentage": 32.699 },
        "#30":  { "Count":   275, "Percentage": 32.699 },
        "#31":  { "Count":   275, "Percentage": 32.699 },
        "#32":  { "Count":   275, "Percentage": 32.699 },
        "#33":  { "Count":   275, "Percentage": 32.699 },
        "#34":  { "Count":   275, "Percentage": 32.699 },
        "#35":  { "Count":   275, "Percentage": 32.699 },
        "#36":  { "Count":   275, "Percentage": 32.699 },
        "#37":  { "Count":   275, "Percentage": 32.699 },
        "#38":  { "Count":   275, "Percentage": 32.699 },
        "#39":  { "Count":   275, "Percentage": 32.699 },
        "#40":  { "Count":   275, "Percentage": 32.699 },
        "#41":  { "Count":   275, "Percentage": 32.699 },
        "#42":  { "Count":   275, "Percentage": 32.699 },
        "#43":  { "Count":   275, "Percentage": 32.699 },
        "#44":  { "Count":   275, "Percentage": 32.699 },
        "#45":  { "Count":   275, "Percentage": 32.699 },
        "#46":  { "Count":   275, "Percentage": 32.699 },
        "#47":  { "Count":   275, "Percentage": 32.699 },
        "#48":  { "Count":   275, "Percentage": 32.699 },
        "#49":  { "Count":    40, "Percentage":  4.756 },
        "#50":  { "Count":    45, "Percentage":  5.351 },
        "#51":  { "Count":    64, "Percentage":  7.610 },
        "#52":  { "Count":    64, "Percentage":  7.610 },
        "#53":  { "Count":    45, "Percentage":  5.351 },
        "#54":  { "Count":    45, "Percentage":  5.351 },
        "#55":  { "Count":    43, "Percentage":  5.113 }
      }
    },
    "ftp" : {
      "Total": { "Count":     0, "Percentage":  0.000 },
      "Signatures": {
        "#1":   { "Count":     0, "Percentage":  0.000 },
        "#2":   { "Count":     0, "Percentage":  0.000 },
        "#3":   { "Count":     0, "Percentage":  0.000 },
        "#4":   { "Count":     0, "Percentage":  0.000 },
        "#5":   { "Count":     0, "Percentage":  0.000 },
        "#6":   { "Count":     0, "Percentage":  0.000 },
        "#7":   { "Count":     0, "Percentage":  0.000 },
        "#8":   { "Count":     0, "Percentage":  0.000 },
        "#9":   { "Count":     0, "Percentage":  0.000 }
      }
    },
    "http" : {
      "Total": { "Count":     1, "Percentage":  0.119 },
      "Redundancy":  1.000,
      "Signatures": {
        "#1":   { "Count":     0, "Percentage":  0.000 },
        "#2":   { "Count":     0, "Percentage":  0.000 },
        "#3":   { "Count":     0, "Percentage":  0.000 },
        "#4":   { "Count":     0, "Percentage":  0.000 },
        "#5":   { "Count":     0, "Percentage":  0.000 },
        "#6":   { "Count":     0, "Percentage":  0.000 },
        "#7":   { "Count":     0, "Percentage":  0.000 },
        "#8":   { "Count":     0, "Percentage":  0.000 },
        "#9":   { "Count":     0, "Percentage":  0.000 },
        "#10":  { "Count":     0, "Percentage":  0.000 },
        "#11":  { "Count":     0, "Percentage":  0.000 },
        "#12":  { "Count":     1, "Percentage":  0.119 },
        "#13":  { "Count":     0, "Percentage":  0.000 },
        "#14":  { "Count":     0, "Percentage":  0.000 },
        "#15":  { "Count":     0, "Percentage":  0.000 },
        "#16":  { "Count":     0, "Percentage":  0.000 },
        "#17":  { "Count":     0, "Percentage":  0.000 },
        "#18":  { "Count":     0, "Percentage":  0.000 },
        "#19":  { "Count":     0, "Percentage":  0.000 },
        "#20":  { "Count":     1, "Percentage":  0.119 },
        "#21":  { "Count":     0, "Percentage":  0.000 },
        "#22":  { "Count":     0, "Percentage":  0.000 },
        "#23":  { "Count":     0, "Percentage":  0.000 },
        "#24":  { "Count":     0, "Percentage":  0.000 },
        "#25":  { "Count":     0, "Percentage":  0.000 },
        "#26":  { "Count":     0, "Percentage":  0.000 },
        "#27":  { "Count":     0, "Percentage":  0.000 },
        "#28":  { "Count":     0, "Percentage":  0.000 },
        "#29":  { "Count":     0, "Percentage":  0.000 },
        "#30":  { "Count":     0, "Percentage":  0.000 },
        "#31":  { "Count":     0, "Percentage":  0.000 },
        "#32":  { "Count":     0, "Percentage":  0.000 },
        "#33":  { "Count":     0, "Percentage":  0.000 },
        "#34":  { "Count":     0, "Percentage":  0.000 },
        "#35":  { "Count":     0, "Percentage":  0.000 },
        "#36":  { "Count":     0, "Percentage":  0.000 },
        "#37":  { "Count":     0, "Percentage":  0.000 },
        "#38":  { "Count":     1, "Percentage":  0.119 },
        "#39":  { "Count":     0, "Percentage":  0.000 },
        "#40":  { "Count":     0, "Percentage":  0.000 },
        "#41":  { "Count":     0, "Percentage":  0.000 },
        "#42":  { "Count":     0, "Percentage":  0.000 },
        "#43":  { "Count":     0, "Percentage":  0.000 },
        "#44":  { "Count":     0, "Percentage":  0.000 },
        "#45":  { "Count":     0, "Percentage":  0.000 },
        "#46":  { "Count":     0, "Percentage":  0.000 },
        "#47":  { "Count":     0, "Percentage":  0.000 },
        "#48":  { "Count":     0, "Percentage":  0.000 },
        "#49":  { "Count":     0, "Percentage":  0.000 },
        "#50":  { "Count":     0, "Percentage":  0.000 },
        "#51":  { "Count":     0, "Percentage":  0.000 },
        "#52":  { "Count":     0, "Percentage":  0.000 },
        "#53":  { "Count":     0, "Percentage":  0.000 },
        "#54":  { "Count":     0, "Percentage":  0.000 },
        "#55":  { "Count":     0, "Percentage":  0.000 },
        "#56":  { "Count":     0, "Percentage":  0.000 },
        "#57":  { "Count":     0, "Percentage":  0.000 },
        "#58":  { "Count":     0, "Percentage":  0.000 },
        "#59":  { "Count":     0, "Percentage":  0.000 },
        "#60":  { "Count":     0, "Percentage":  0.000 },
        "#61":  { "Count":     0, "Percentage":  0.000 },
        "#62":  { "Count":     0, "Percentage":  0.000 },
        "#63":  { "Count":     0, "Percentage":  0.000 },
        "#64":  { "Count":     0, "Percentage":  0.000 },
        "#65":  { "Count":     0, "Percentage":  0.000 },
        "#66":  { "Count":     0, "Percentage":  0.000 },
        "#67":  { "Count":     1, "Percentage":  0.119 },
        "#68":  { "Count":     0, "Percentage":  0.000 },
        "#69":  { "Count":     1, "Percentage":  0.119 },
        "#70":  { "Count":     0, "Percentage":  0.000 },
        "#71":  { "Count":     0, "Percentage":  0.000 },
        "#72":  { "Count":     0, "Percentage":  0.000 },
        "#73":  { "Count":     0, "Percentage":  0.000 },
        "#74":  { "Count":     0, "Percentage":  0.000 },
        "#75":  { "Count":     0, "Percentage":  0.000 },
        "#76":  { "Count":     0, "Percentage":  0.000 },
        "#77":  { "Count":     0, "Percentage":  0.000 },
        "#78":  { "Count":     0, "Percentage":  0.000 },
        "#79":  { "Count":     0, "Percentage":  0.000 },
        "#80":  { "Count":     0, "Percentage":  0.000 },
        "#81":  { "Count":     1, "Percentage":  0.119 },
        "#82":  { "Count":     0, "Percentage":  0.000 },
        "#83":  { "Count":     0, "Percentage":  0.000 },
        "#84":  { "Count":     1, "Percentage":  0.119 },
        "#85":  { "Count":     0, "Percentage":  0.000 },
        "#86":  { "Count":     0, "Percentage":  0.000 },
        "#87":  { "Count":     0, "Percentage":  0.000 },
        "#88":  { "Count":     0, "Percentage":  0.000 },
        "#89":  { "Count":     0, "Percentage":  0.000 },
        "#90":  { "Count":     1, "Percentage":  0.119 },
        "#91":  { "Count":     0, "Percentage":  0.000 },
        "#92":  { "Count":     0, "Percentage":  0.000 },
        "#93":  { "Count":     0, "Percentage":  0.000 },
        "#94":  { "Count":     1, "Percentage":  0.119 },
        "#95":  { "Count":     0, "Percentage":  0.000 },
        "#96":  { "Count":     0, "Percentage":  0.000 },
        "#97":  { "Count":     0, "Percentage":  0.000 },
        "#98":  { "Count":     0, "Percentage":  0.000 },
        "#99":  { "Count":     0, "Percentage":  0.000 },
        "#100": { "Count":     0, "Percentage":  0.000 },
        "#101": { "Count":     0, "Percentage":  0.000 },
        "#102": { "Count":     0, "Percentage":  0.000 },
        "#103": { "Count":     0, "Percentage":  0.000 },
        "#104": { "Count":     0, "Percentage":  0.000 },
        "#105": { "Count":     0, "Percentage":  0.000 },
        "#106": { "Count":     0, "Percentage":  0.000 },
        "#107": { "Count":     0, "Percentage":  0.000 },
        "#108": { "Count":     0, "Percentage":  0.000 },
        "#109": { "Count":     0, "Percentage":  0.000 },
        "#110": { "Count":     1, "Percentage":  0.119 },
        "#111": { "Count":     0, "Percentage":  0.000 },
        "#112": { "Count":     0, "Percentage":  0.000 },
        "#113": { "Count":     0, "Percentage":  0.000 },
        "#114": { "Count":     0, "Percentage":  0.000 },
        "#115": { "Count":     0, "Percentage":  0.000 },
        "#116": { "Count":     0, "Percentage":  0.000 },
        "#117": { "Count":     1, "Percentage":  0.119 },
        "#118": { "Count":     0, "Percentage":  0.000 },
        "#119": { "Count":     0, "Percentage":  0.000 },
        "#120": { "Count":     1, "Percentage":  0.119 },
        "#121": { "Count":     0, "Percentage":  0.000 },
        "#122": { "Count":     0, "Percentage":  0.000 },
        "#123": { "Count":     1, "Percentage":  0.119 },
        "#124": { "Count":     0, "Percentage":  0.000 },
        "#125": { "Count":     1, "Percentage":  0.119 },
        "#126": { "Count":     0, "Percentage":  0.000 },
        "#127": { "Count":     0, "Percentage":  0.000 },
        "#128": { "Count":     0, "Percentage":  0.000 },
        "#129": { "Count":     0, "Percentage":  0.000 },
        "#130": { "Count":     0, "Percentage":  0.000 }
      }
    },
    "other" : {
      "Total": { "Count":    11, "Percentage":  1.308 }
    }
  }
}
